CHANGELOG.md
LICENSE
MANIFEST.in
README.md
setup.py
shufflecad/__init__.py
shufflecad/connections.py
shufflecad/logger.py
shufflecad/shared.py
shufflecad/shufflecad.py
shufflecad_py.egg-info/PKG-INFO
shufflecad_py.egg-info/SOURCES.txt
shufflecad_py.egg-info/dependency_links.txt
shufflecad_py.egg-info/requires.txt
shufflecad_py.egg-info/top_level.txt