Metadata-Version: 1.1
Name: shufflecad-py
Version: 0.0.0.6
Summary: python lib for shufflecad
Home-page: https://github.com/Soft-V/shufflecad-4
Author: Abdrakov Airat
Author-email: abdrakovairat@gmail.com
License: MIT
Keywords: simulator,robotics,robot,3d,raspberry,control
Platform: UNKNOWN
Classifier: Development Status :: 5 - Production/Stable
Classifier: Intended Audience :: Education
Classifier: Operating System :: Microsoft :: Windows :: Windows 10
Classifier: License :: OSI Approved :: MIT License
Classifier: Programming Language :: Python :: 3
